leetcodehelper/__init__.py
leetcodehelper/main.py
leetcodehelper/driver/__init__.py
leetcodehelper/driver/installer.py
leetcodehelper/utils/__init__.py
leetcodehelper/utils/settings.py
leetcodehelper/utils/tools.py
leetcodeHelper-0.0.1.dist-info/LICENSE
leetcodeHelper-0.0.1.dist-info/METADATA
leetcodeHelper-0.0.1.dist-info/WHEEL
leetcodeHelper-0.0.1.dist-info/entry_points.txt
leetcodeHelper-0.0.1.dist-info/top_level.txt
leetcodeHelper-0.0.1.dist-info/RECORD
