Metadata-Version: 2.1
Name: leetcodeHelper
Version: 0.0.1
Summary: Friendly leecode interface
Home-page: https://github.com/harry83017622/leetcodeHelper
Author: Cheng-Hao Lee
Author-email: chenghaolee0125@gmail.com
License: UNKNOWN
Download-URL: https://github.com/harry83017622/leetcodeHelper/archive/refs/tags/0.0.1.tar.gz
Platform: UNKNOWN
Classifier: Programming Language :: Python :: 3
Classifier: License :: OSI Approved :: MIT License
Classifier: Operating System :: Microsoft :: Windows
Classifier: Operating System :: POSIX :: Linux
Classifier: Operating System :: MacOS
Classifier: Programming Language :: Python :: 3.6
Classifier: Programming Language :: Python :: 3.7
Classifier: Programming Language :: Python :: 3.8
Classifier: Programming Language :: Python :: 3.9
Requires-Python: >=3.6
Requires-Dist: beautifulsoup4 (==4.9.3)
Requires-Dist: selenium (==3.141.0)
